DLNAmpvRenderer/DLNAmpvRenderer.py
DLNAmpvRenderer/README.md
DLNAmpvRenderer/__init__.py
DLNAmpvRenderer/icon.png
DLNAmpvRenderer/mpv.bat
DLNAmpvRenderer-1.3.2.dist-info/LICENSE
DLNAmpvRenderer-1.3.2.dist-info/METADATA
DLNAmpvRenderer-1.3.2.dist-info/WHEEL
DLNAmpvRenderer-1.3.2.dist-info/top_level.txt
DLNAmpvRenderer-1.3.2.dist-info/RECORD
