Metadata-Version: 2.1
Name: DLNAmpvRenderer
Version: 1.3.2
Summary: A script in Python 3 to turn mpv into a DLNA / UPnP renderer
Home-page: https://github.com/PCigales/DLNAmpvRenderer
Author: PCigales
License: GNU GPLv3
Project-URL: Bug Tracker, https://github.com/PCigales/DLNAmpvRenderer/issues
Platform: win64
Classifier: Programming Language :: Python :: 3
Classifier: License :: OSI Approved :: GNU General Public License v3 or later (GPLv3+)
Classifier: Operating System :: Microsoft :: Windows
Classifier: Development Status :: 5 - Production/Stable
Classifier: Topic :: Multimedia :: Video
Classifier: Topic :: Multimedia :: Sound/Audio
Requires-Python: >=3.7
License-File: LICENSE
